vkOsint/__init__.py
vkOsint/exceptions.py
vkOsint/mixins/__init__.py
vkOsint/mixins/api.py
vkOsint/mixins/parsers.py
vkOsint/mixins/utils.py
vkOsint-1.0.dist-info/LICENSE
vkOsint-1.0.dist-info/METADATA
vkOsint-1.0.dist-info/WHEEL
vkOsint-1.0.dist-info/top_level.txt
vkOsint-1.0.dist-info/RECORD
