Metadata-Version: 2.1
Name: vkOsint
Version: 1.0
Summary: Python package for searching vk accounts by phone number
Home-page: https://github.com/DIJIRO/vkOsint
Author: DIJIRO
Author-email: de.sm1rnov@yandex.ru
License: MIT
Keywords: vk private api,vk osint,vkOsint,vk-api
Classifier: Programming Language :: Python :: 3.10
Classifier: License :: OSI Approved :: MIT License
Classifier: Operating System :: OS Independent
Classifier: Topic :: Software Development :: Libraries :: Python Modules
Requires-Python: >=3.10
License-File: LICENSE
Requires-Dist: PySocks (==1.7.1)
Requires-Dist: requests (==2.28.2)
Requires-Dist: urllib3 (==1.26.14)
